[
  {
    "image": "image1",
    "name": "Skills",
    "price": "Software Developer",
    "bullets": [
      "JavaScript || React.js || HTML || CSS || Node.js",
      "Web Applications",
      "Databases (PostgreSQL)",
      "Teamwork",
      "Software Development Life Cycle (SDLC)",
      "Agile Methodologies, Scrum, Remote Collaboration Tools",
      "Problem-solving",
      "AWS || C# || .Net"
    ]
  },
  {
    "image": "image2",
    "name": "PROFESSIONAL EXPERIENCE",
    "price": " ",
    "bullets": [
      "01/2004 - 02/2024 || Trainee || Full-Stack Development Level 5 || Gateshead College",
      "08/2023 - 10/2023 || Trainee || AWS Re-start || Prime Talent",
      "03/2023 - 04/2023 || Full-Stack Developer || Code Your Future",
      "02/2022 - 04/2023 || Trainee || Full-Stack Web Development || Code Your Future",
      "09/2015 - 12/2019 || First Lieutenant || Logistic Units || Turkish Air Forces", 
      "09/2009 - 09-2015 || Petty Officer|| Logistic Units || Turkish Air Forces",
      "Automatic tailgate operation"
    ]
  },
  {
    "image": "image3",
    "name": "Education",
    "price": "",
    "bullets": [
      "04/2022 – 04/2023 || Full-Stack Software Development || Code Your Future",
      "2010 – 2014 || Bachelor's Degree || Business Administration || Anadolu University",
      "09/2007 – 08/2009 || Associate's Degree || Air NCO Higher Vocational School || Turkish Air Forces"
    ]
  }
]
